dfasat
