Metadata-Version: 1.0
Name: dfasat
Version: 0.0.1.44
Summary: DFASAT
Home-page: UNKNOWN
Author: Christian Hammerschmidt, Benjamin Loos
Author-email: christian.hammerschmidt@uni.lu, loos.benjamin@gmail.com
License: UNKNOWN
Platform: UNKNOWN
